CHANGELOG.rst
CONTRIBUTING.rst
LICENSE
MANIFEST.in
NOTICE
README.rst
setup.cfg
setup.py
chalice/__init__.py
chalice/analyzer.py
chalice/app.py
chalice/awsclient.py
chalice/compat.py
chalice/config.py
chalice/constants.py
chalice/invoke.py
chalice/local.py
chalice/logs.py
chalice/package.py
chalice/pipeline.py
chalice/policies-extra.json
chalice/policies-extra.yml
chalice/policies.json
chalice/policies.yml
chalice/policy.py
chalice/utils.py
chalice/cli/__init__.py
chalice/cli/factory.py
chalice/cli/reloader.py
chalice/cli/filewatch/__init__.py
chalice/cli/filewatch/eventbased.py
chalice/cli/filewatch/stat.py
chalice/deploy/__init__.py
chalice/deploy/deployer.py
chalice/deploy/executor.py
chalice/deploy/models.py
chalice/deploy/packager.py
chalice/deploy/planner.py
chalice/deploy/swagger.py
chalice/deploy/validate.py
parfait.egg-info/PKG-INFO
parfait.egg-info/SOURCES.txt
parfait.egg-info/dependency_links.txt
parfait.egg-info/entry_points.txt
parfait.egg-info/not-zip-safe
parfait.egg-info/requires.txt
parfait.egg-info/top_level.txt