Metadata-Version: 2.1
Name: parfait
Version: 0.3
Summary: Microframework
Home-page: https://github.com/aws/chalice
Author: James Saryerwinnie
Author-email: js@jamesls.com
License: Apache License 2.0
Keywords: chalice,parfait,aws,lambda,amazon web services
Platform: UNKNOWN
Classifier: Development Status :: 5 - Production/Stable
Classifier: Intended Audience :: Developers
Classifier: License :: OSI Approved :: Apache Software License
Classifier: Natural Language :: English
Classifier: Programming Language :: Python :: 3
Classifier: Programming Language :: Python :: 3.6
Classifier: Programming Language :: Python :: 3.7
Provides-Extra: event-file-poller
